MANIFEST.in
README
setup.py
MAST/__init__.py
MAST/_version.py
MAST.egg-info/PKG-INFO
MAST.egg-info/SOURCES.txt
MAST.egg-info/dependency_links.txt
MAST.egg-info/requires.txt
MAST.egg-info/top_level.txt
MAST/bin/__init__.py
MAST/bin/mast
MAST/bin/mast_diffusion_coefficient
MAST/bin/mast_finite_size_scaling_sizes
MAST/bin/mast_madelung_utility
MAST/controllers/__init__.py
MAST/controllers/mastinput.py
MAST/controllers/mastmon.py
MAST/controllers/modifyrecipe.py
MAST/data/__init__.py
MAST/doc/__init__.py
MAST/doc/run_sphinx_apidoc.py
MAST/examples/POSCAR.ga4as4
MAST/examples/README
MAST/examples/charged_defects_with_scaling.inp
MAST/examples/neb_int_and_sub_test.inp
MAST/examples/neb_with_phonons.inp
MAST/examples/neb_with_phonons_pathfinder.inp
MAST/examples/simple_optimization.inp
MAST/examples/testing_1.3
MAST/examples/u_ramping.inp
MAST/ingredients/__init__.py
MAST/ingredients/baseingredient.py
MAST/ingredients/chopingredient.py
MAST/ingredients/checker/__init__.py
MAST/ingredients/checker/basechecker.py
MAST/ingredients/checker/genericchecker.py
MAST/ingredients/checker/lammpschecker.py
MAST/ingredients/checker/lammpschecker_v1.py
MAST/ingredients/checker/phonchecker.py
MAST/ingredients/checker/structoptchecker.py
MAST/ingredients/checker/vaspchecker.py
MAST/ingredients/checker/vaspnebchecker.py
MAST/ingredients/errorhandler/__init__.py
MAST/ingredients/errorhandler/baseerror.py
MAST/ingredients/errorhandler/genericerror.py
MAST/ingredients/errorhandler/masterrorhandlers.py
MAST/ingredients/errorhandler/mastvasperrorhandlers.py
MAST/ingredients/errorhandler/phonerror.py
MAST/ingredients/errorhandler/vasperror.py
MAST/ingredients/errorhandler/vaspneberror.py
MAST/ingredients/pmgextend/__init__.py
MAST/ingredients/pmgextend/atom_index.py
MAST/ingredients/pmgextend/procar_parse_occ.py
MAST/ingredients/pmgextend/procar_parse_occ_spin.py
MAST/ingredients/pmgextend/structure_extensions.py
MAST/ingredients/programkeys/README
MAST/ingredients/programkeys/__init__.py
MAST/ingredients/programkeys/diff_allowed_keywords.py
MAST/ingredients/programkeys/lammps_allowed_keywords.py
