Metadata-Version: 1.0
Name: MAST
Version: 2.0.1
Summary: MAterials Simulation Toolkit
Home-page: https://materialshub.org
Author: MAST Development Team, University of Wisconsin-Madison Computational Materials Group
Author-email: ddmorgan@wisc.edu
License: MIT
Keywords: MAST,materials,simulation,diffusion,defects,ab initio,high throughput,DFT,density functional theory,defect formation
Platform: UNKNOWN
